example_package/__init__.py
example_package/example.py
Auto_cui-0.0.6.dist-info/LICENSE
Auto_cui-0.0.6.dist-info/METADATA
Auto_cui-0.0.6.dist-info/WHEEL
Auto_cui-0.0.6.dist-info/top_level.txt
Auto_cui-0.0.6.dist-info/RECORD
