Metadata-Version: 2.1
Name: Auto-cui
Version: 0.0.6
Summary: A small example package
Home-page: https://github.com/SynchronyML/protein_lucky
Author: Cui Zy
Author-email: 1776228595@qq.com
License: UNKNOWN
Project-URL: Bug Tracker, https://github.com/SynchronyML/protein_lucky/issues
Platform: UNKNOWN
Classifier: Programming Language :: Python :: 3
Classifier: License :: OSI Approved :: MIT License
Classifier: Operating System :: OS Independent
Requires-Python: >=3.6
License-File: LICENSE
Requires-Dist: numpy (>=1.11.0)
